{"expireTime":9007200882617060000,"key":"7804fa1c15f53c0bf9da49787897a45f","val":{"name":"IMAGE_PROCESSING","inputPaths":["/Users/peterlow/Desktop/Portfolio_v3/src/images/md.png"],"outputDir":"/Users/peterlow/Desktop/Portfolio_v3/public/static/c6f39662eb87c9680d558bf3bd06e328","args":{"isLazy":false,"operations":[{"outputPath":"8080f/md.png","args":{"width":342,"cropFocus":17,"toFormat":"png","fit":"cover","background":"rgba(0,0,0,1)"}},{"outputPath":"3ff62/md.png","args":{"width":683,"cropFocus":17,"toFormat":"png","fit":"cover","background":"rgba(0,0,0,1)"}},{"outputPath":"43fa5/md.png","args":{"width":1366,"cropFocus":17,"toFormat":"png","fit":"cover","background":"rgba(0,0,0,1)"}},{"outputPath":"9337f/md.png","args":{"width":2049,"cropFocus":17,"toFormat":"png","fit":"cover","background":"rgba(0,0,0,1)"}},{"outputPath":"4a4e2/md.png","args":{"width":2254,"cropFocus":17,"toFormat":"png","fit":"cover","background":"rgba(0,0,0,1)"}}],"pluginOptions":{"base64Width":20,"forceBase64Format":"","useMozJpeg":false,"stripMetadata":true,"lazyImageGeneration":true,"defaultQuality":50,"failOnError":true,"plugins":[]}}}}